onzr/__init__.py
onzr/cli.py
onzr/client.py
onzr/config.py
onzr/core.py
onzr/deezer.py
onzr/exceptions.py
onzr/server.py
onzr/settings.yaml.dist
onzr/models/__init__.py
onzr/models/core.py
onzr/models/deezer.py
onzr-0.6.0.dist-info/METADATA
onzr-0.6.0.dist-info/WHEEL
onzr-0.6.0.dist-info/entry_points.txt
onzr-0.6.0.dist-info/licenses/LICENSE
onzr-0.6.0.dist-info/RECORD
