Metadata-Version: 2.4
Name: onzr
Version: 0.6.0
Summary: The one-hour-late Deezer CLI.
Project-URL: Repository, https://github.com/jmaupetit/onzr
Author-email: Julien Maupetit <julien@maupetit.net>
License-Expression: MIT
License-File: LICENSE
Keywords: audio,cli,deezer,flac,mp3,tui
Classifier: Development Status :: 3 - Alpha
Classifier: Topic :: Multimedia :: Sound/Audio :: Players
Classifier: Topic :: Terminals
Requires-Python: <4.0.0,>3.10
Requires-Dist: deezer-py<2,>=1.3.7
Requires-Dist: fastapi<0.124,>=0.123.8
Requires-Dist: pendulum>=3.1.0
Requires-Dist: pycryptodomex<4,>=3.21.0
Requires-Dist: pydantic-extra-types>=2.10.6
Requires-Dist: pydantic-settings<3,>=2.9.1
Requires-Dist: python-vlc<4,>=3.0.21203
Requires-Dist: typer<0.21,>=0.20
Requires-Dist: uvicorn[standard]<0.39,>=0.38
